iotrelay_influxdb.py
iotrelay_influxdb-1.7.0.dist-info/DESCRIPTION.rst
iotrelay_influxdb-1.7.0.dist-info/METADATA
iotrelay_influxdb-1.7.0.dist-info/RECORD
iotrelay_influxdb-1.7.0.dist-info/WHEEL
iotrelay_influxdb-1.7.0.dist-info/entry_points.txt
iotrelay_influxdb-1.7.0.dist-info/metadata.json
iotrelay_influxdb-1.7.0.dist-info/top_level.txt
