Metadata-Version: 2.0
Name: iotrelay-influxdb
Version: 1.7.0
Summary: InfluxDB handler module for iotrelay
Home-page: https://github.com/eman/iotrelay-influxdb
Author: Emmanuel Levijarvi
Author-email: emansl@gmail.com
License: BSD
Keywords: influxdb IoT
Platform: UNKNOWN
Classifier: Development Status :: 4 - Beta
Classifier: Intended Audience :: Developers
Classifier: Topic :: Home Automation
Classifier: Topic :: Utilities
Classifier: License :: OSI Approved :: BSD License
Classifier: Operating System :: OS Independent
Classifier: Programming Language :: Python :: 2.7
Requires-Dist: iotrelay (>=1.2)
Requires-Dist: influxdb (>=3.0.0)
